README.rst
setup.cfg
setup.py
convict/__init__.py
convict.egg-info/PKG-INFO
convict.egg-info/SOURCES.txt
convict.egg-info/dependency_links.txt
convict.egg-info/top_level.txt