Metadata-Version: 1.1
Name: convict
Version: 0.2
Summary: python clone of node-convict (https://github.com/mozilla/node-convict)
Home-page: UNKNOWN
Author: Daniel Thornton
Author-email: daniel@relud.com
License: MPL 2.0
Platform: UNKNOWN
Classifier: Development Status :: 3 - Alpha
Classifier: Programming Language :: Python :: 2
Classifier: Programming Language :: Python :: 3
